{
  "\"Chess is the gymnasium of the mind.\" - Blaise Pascal": "TRADUZIR",
  "\"Even a poor plan is better than no plan at all.\" - Mikhail Chigorin": "TRADUZIR",
  "A classic, eh? Battling for the center, just like Fischer. Let's see what you've got.": "TRADUZIR",
  "A decent enough choice by them, though I think they definitely had something better.": "TRADUZIR",
  "Alright, your opponent's challenging the center to fight for space. Good for them.": "TRADUZIR",
  "Capturing that queen wins material.": "TRADUZIR",
  "English chess masters were recruited as code breakers during World War II.": "TRADUZIR",
  "Free bishop coming right up, nice fork .": "TRADUZIR",
  "Free pawn, my favorite kind.": "TRADUZIR",
  "Moving the same piece again? Not very efficient, I must say. Their better move was to send a rook into the game.": "TRADUZIR",
  "Not bad, but could be better. I've seen worse though, trust me.": "TRADUZIR",
  "Oh, they messed up, huh? Your opponent's bishop is now lost. Take it, take it.": "TRADUZIR",
  "Oh, they messed up, huh? Your opponent's knight is now lost. Take it, take it.": "TRADUZIR",
  "Oh, they messed up, huh? Your opponent's queen is now lost. Take it, take it.": "TRADUZIR",
  "Oh, they messed up, huh? Your opponent's rook is now lost. Take it, take it.": "TRADUZIR",
  "Ok, your opponent found the only move. Congrats to them?": "TRADUZIR",
  "Slipping away from that check, nice.": "TRADUZIR",
  "Smart move, getting that bishop to safety like a boss.": "TRADUZIR",
  "Smooth escape. You've managed to keep that queen alive.": "TRADUZIR",
  "That's how you gain space in the center. Now your pieces have room to breathe.": "TRADUZIR",
  "Their bishop's now more active , eh? Good for them, I guess?": "TRADUZIR",
  "Their knight moves into play. Let's see what that will do.": "TRADUZIR",
  "Your best move was to increase a bishop's scope by moving it to a better square.": "TRADUZIR",
  "Your better option was to increase a bishop's scope by moving it to a better square.": "TRADUZIR",
  "Your opening and tactic were slick. You found victory.": "TRADUZIR",
  "Your opponent left their bishop hanging ? Looks like it's free. Take it.": "TRADUZIR",
  "Your opponent's pawn push? Well, now you gotta react in the center.": "TRADUZIR",
  "Your opponent's pinned your knight, limiting its movement. Tricky.": "TRADUZIR",
  "Your opponent's preparing to bring their bishop into the game. Let's see how that goes.": "TRADUZIR",
  "You're making them work for it. Nice defense.": "TRADUZIR"
}