{
  "Ah, e4. I can dig it. Center control right off the bat, the bishop's free. Good stuff.": "TRADUZIR",
  "Ah, your opponent's going hypermodern, huh?": "TRADUZIR",
  "Good, taking central space . That's how you claim your territory on the board.": "TRADUZIR",
  "If \"rook\" comes from the Persian word \"rukh\" meaning chariot, why does the piece look like a tower?": "TRADUZIR",
  "The Sicilian Defense is the most popular response to 1.e4.": "TRADUZIR",
  "The game was close to equal, but now Black has the advantage.": "TRADUZIR",
  "The knight is now adequately defended .": "TRADUZIR",
  "You were merciless until the end. Nice win.": "TRADUZIR"
}